aiotaskqueue/__init__.py
aiotaskqueue/_types.py
aiotaskqueue/_util.py
aiotaskqueue/config.py
aiotaskqueue/errors.py
aiotaskqueue/extensions.py
aiotaskqueue/logging.py
aiotaskqueue/publisher.py
aiotaskqueue/py.typed
aiotaskqueue/router.py
aiotaskqueue/tasks.py
aiotaskqueue/types.py
aiotaskqueue/worker.py
aiotaskqueue/broker/__init__.py
aiotaskqueue/broker/abc.py
aiotaskqueue/broker/inmemory.py
aiotaskqueue/broker/redis.py
aiotaskqueue/broker/sql/__init__.py
aiotaskqueue/broker/sql/sqlalchemy/__init__.py
aiotaskqueue/broker/sql/sqlalchemy/_utils.py
aiotaskqueue/broker/sql/sqlalchemy/broker.py
aiotaskqueue/broker/sql/sqlalchemy/models.py
aiotaskqueue/experimental/__init__.py
aiotaskqueue/experimental/reduce.py
aiotaskqueue/experimental/sequential.py
aiotaskqueue/extensions/__init__.py
aiotaskqueue/extensions/abc.py
aiotaskqueue/extensions/middleware.py
aiotaskqueue/extensions/builtin/__init__.py
aiotaskqueue/extensions/builtin/retry.py
aiotaskqueue/extensions/builtin/time_limit.py
aiotaskqueue/result/__init__.py
aiotaskqueue/result/abc.py
aiotaskqueue/result/inmemory.py
aiotaskqueue/result/redis.py
aiotaskqueue/result/sql/__init__.py
aiotaskqueue/result/sql/sqlalchemy/__init__.py
aiotaskqueue/result/sql/sqlalchemy/backend.py
aiotaskqueue/result/sql/sqlalchemy/models.py
aiotaskqueue/scheduled_broker/__init__.py
aiotaskqueue/scheduled_broker/abc.py
aiotaskqueue/scheduled_broker/inmemory.py
aiotaskqueue/scheduled_broker/redis.py
aiotaskqueue/scheduled_broker/scheduler.py
aiotaskqueue/scheduled_broker/sql/__init__.py
aiotaskqueue/scheduled_broker/sql/sqlalchemy/__init__.py
aiotaskqueue/scheduled_broker/sql/sqlalchemy/models.py
aiotaskqueue/scheduled_broker/sql/sqlalchemy/schedulerd_broker.py
aiotaskqueue/scheduler/__init__.py
aiotaskqueue/scheduler/_scheduler.py
aiotaskqueue/scheduler/abc.py
aiotaskqueue/scheduler/schedules.py
aiotaskqueue/serialization/__init__.py
aiotaskqueue/serialization/_serialization.py
aiotaskqueue/serialization/msgspec.py
aiotaskqueue-0.15.0.dist-info/METADATA
aiotaskqueue-0.15.0.dist-info/WHEEL
aiotaskqueue-0.15.0.dist-info/top_level.txt
aiotaskqueue-0.15.0.dist-info/RECORD
