Metadata-Version: 2.4
Name: aiotaskqueue
Version: 0.15.0
Summary: Asynchronous task queue framework
Author-email: Doctor <thirvondukr@gmail.com>
License: MIT
Project-URL: Repository, https://github.com/ThirVondukr/aiotaskqueue
Project-URL: Issues, https://github.com/ThirVondukr/aiotaskqueue/issues
Requires-Python: >=3.11
Requires-Dist: anyio>=4.6.2.post1
Requires-Dist: msgspec>=0.19.0
Requires-Dist: typing-extensions>=4.8.0
Provides-Extra: redis
Requires-Dist: redis>=6.0.0; extra == "redis"
Provides-Extra: scheduler
Requires-Dist: croniter>=6.0.0; extra == "scheduler"
Provides-Extra: sqlalchemy
Requires-Dist: sqlalchemy[asyncio]>=2.0.43; extra == "sqlalchemy"
